[
    {
      "journal": "Nat. Commun.",
      "title": "<a href='https://doi.org/10.1038/s41467-018-05771-8'>Galectin-9 binds IgM-BCR to regulate B cell signaling</a>",
      "year": "2018"
    },
    {
      "journal": "PNAS",
      "title": "<a href='https://doi.org/10.1073/pnas.0437939100'>IL-1 is required for tumor invasiveness and angiogenesis</a>",
      "year": "2003"
    },
    {
      "journal": "Biochem. Eng. J.",
      "title": "<a href='https://doi.org/10.1016/S1369-703X(97)00014-4'>Fed-batch production of L-lysine by <i>Corynebacterium glutamicum</i></a>",
      "year": "2018"
    },
    {
      "journal": "Microbiol. Res.",
      "title": "<a href='https://doi.org/10.1016/j.micres.2022.127101'>Industrial production of L-lysine in <i>Corynebacterium glutamicum</i>: Progress and prospects</a>",
      "year": "2022"
    },
    {
      "journal": "Nat. Biotechnol.",
      "title": "<a href='https://doi.org/10.1038/s41587-021-01195-w'>Carbon-negative production of acetone and isopropanol by gas fermentation at industrial pilot scale</a>",
      "year": "2021"
    }
  ]
  